LICENSE
MANIFEST.in
README.md
setup.py
computepipfilehash/__init__.py
computepipfilehash.egg-info/PKG-INFO
computepipfilehash.egg-info/SOURCES.txt
computepipfilehash.egg-info/dependency_links.txt
computepipfilehash.egg-info/entry_points.txt
computepipfilehash.egg-info/top_level.txt