Metadata-Version: 2.1
Name: computepipfilehash
Version: 0.0.3
Summary: To generate requirements file with hashes.
Home-page: https://github.com/kushaldas/computepipfilehash
Author: Kushal Das
Author-email: mail@kushaldas.in
License: GPLv3+
Platform: UNKNOWN
Classifier: Development Status :: 3 - Alpha
Classifier: Programming Language :: Python :: 3
Classifier: Topic :: Software Development :: Libraries :: Python Modules
Classifier: License :: OSI Approved :: GNU General Public License v3 or later (GPLv3+)
Classifier: Intended Audience :: Developers
Classifier: Operating System :: OS Independent
Requires-Python: >=3.5
